README.rst
setup.py
actstream_autoactor/__init__.py
actstream_autoactor/autoconfig.py
actstream_autoactor/middleware.py
actstream_autoactor/models.py
actstream_autoactor/tests.py
actstream_autoactor/utils.py
actstream_autoactor/version.py
actstream_autoactor/migrations/0001_initial.py
actstream_autoactor/migrations/__init__.py
django_activity_stream_autoactor.egg-info/PKG-INFO
django_activity_stream_autoactor.egg-info/SOURCES.txt
django_activity_stream_autoactor.egg-info/dependency_links.txt
django_activity_stream_autoactor.egg-info/requires.txt
django_activity_stream_autoactor.egg-info/top_level.txt