Metadata-Version: 1.1
Name: django-activity-stream-autoactor
Version: 0.0.5
Summary: Automatic provision of actors for django-activity-stream
Home-page: https://github.com/mikebryant/django-activity-stream-autoactor/
Author: Mike Bryant
Author-email: mike@mikebryant.me.uk
License: UNKNOWN
Platform: UNKNOWN
Classifier: Framework :: Django
Classifier: Intended Audience :: Developers
Classifier: Programming Language :: Python
Classifier: Topic :: Software Development :: Libraries :: Python Modules
